{"jump_over":{"agent_falls":{"the_patient":0,"the_agent":27,"it":17,"zero":58},"patient_falls":{"the_agent":0,"the_patient":77,"it":2,"zero":4}},"wave":{"agent_falls":{"the_patient":0,"the_agent":44,"it":26,"zero":37},"patient_falls":{"the_agent":0,"the_patient":105,"it":3,"zero":0}},"attack":{"agent_falls":{"the_patient":0,"the_agent":37,"it":16,"zero":56},"patient_falls":{"the_agent":0,"the_patient":62,"it":9,"zero":1}},"throw_rock":{"agent_falls":{"the_patient":0,"the_agent":87,"it":12,"zero":10},"patient_falls":{"the_agent":0,"the_patient":78,"it":5,"zero":1}},"overall":{"agent_falls":{"the_patient":0,"the_agent":195,"it":71,"zero":161},"patient_falls":{"the_agent":0,"the_patient":322,"it":19,"zero":6}}}